<?xml version="1.0" encoding="UTF-8"?>
<!DOCTYPE mapper PUBLIC "-//mybatis.org//DTD Mapper 3.0//EN" "http://mybatis.org/dtd/mybatis-3-mapper.dtd">
<mapper namespace="com.dianrong.common.uniauth.server.data.mapper.PermissionMapper">
  <resultMap id="BaseResultMap" type="com.dianrong.common.uniauth.server.data.entity.Permission">
    <!--
      WARNING - @mbggenerated
      This element is automatically generated by MyBatis Generator, do not modify.
      This element was generated on Tue Sep 27 11:53:21 CST 2016.
    -->
    <id column="id" jdbcType="INTEGER" property="id" />
    <result column="value" jdbcType="VARCHAR" property="value" />
    <result column="value_ext" jdbcType="VARCHAR" property="valueExt" />
    <result column="description" jdbcType="VARCHAR" property="description" />
    <result column="status" jdbcType="TINYINT" property="status" />
    <result column="perm_type_id" jdbcType="INTEGER" property="permTypeId" />
    <result column="domain_id" jdbcType="INTEGER" property="domainId" />
    <result column="tenancy_id" jdbcType="BIGINT" property="tenancyId" />
  </resultMap>
  <sql id="Example_Where_Clause">
    <!--
      WARNING - @mbggenerated
      This element is automatically generated by MyBatis Generator, do not modify.
      This element was generated on Tue Sep 27 11:53:21 CST 2016.
    -->
    <where>
      <foreach collection="oredCriteria" item="criteria" separator="or">
        <if test="criteria.valid">
          <trim prefix="(" prefixOverrides="and" suffix=")">
            <foreach collection="criteria.criteria" item="criterion">
              <choose>
                <when test="criterion.noValue">
                  and ${criterion.condition}
                </when>
                <when test="criterion.singleValue">
                  and ${criterion.condition} #{criterion.value}
                </when>
                <when test="criterion.betweenValue">
                  and ${criterion.condition} #{criterion.value} and #{criterion.secondValue}
                </when>
                <when test="criterion.listValue">
                  and ${criterion.condition}
                  <foreach close=")" collection="criterion.value" item="listItem" open="(" separator=",">
                    #{listItem}
                  </foreach>
                </when>
              </choose>
            </foreach>
          </trim>
        </if>
      </foreach>
    </where>
  </sql>
  <sql id="Update_By_Example_Where_Clause">
    <!--
      WARNING - @mbggenerated
      This element is automatically generated by MyBatis Generator, do not modify.
      This element was generated on Tue Sep 27 11:53:21 CST 2016.
    -->
    <where>
      <foreach collection="example.oredCriteria" item="criteria" separator="or">
        <if test="criteria.valid">
          <trim prefix="(" prefixOverrides="and" suffix=")">
            <foreach collection="criteria.criteria" item="criterion">
              <choose>
                <when test="criterion.noValue">
                  and ${criterion.condition}
                </when>
                <when test="criterion.singleValue">
                  and ${criterion.condition} #{criterion.value}
                </when>
                <when test="criterion.betweenValue">
                  and ${criterion.condition} #{criterion.value} and #{criterion.secondValue}
                </when>
                <when test="criterion.listValue">
                  and ${criterion.condition}
                  <foreach close=")" collection="criterion.value" item="listItem" open="(" separator=",">
                    #{listItem}
                  </foreach>
                </when>
              </choose>
            </foreach>
          </trim>
        </if>
      </foreach>
    </where>
  </sql>
  <sql id="Base_Column_List">
    <!--
      WARNING - @mbggenerated
      This element is automatically generated by MyBatis Generator, do not modify.
      This element was generated on Tue Sep 27 11:53:21 CST 2016.
    -->
    id, value, value_ext, description, status, perm_type_id, domain_id, tenancy_id
  </sql>
  <select id="selectByExample" parameterType="com.dianrong.common.uniauth.server.data.entity.PermissionExample" resultMap="BaseResultMap">
    <!--
      WARNING - @mbggenerated
      This element is automatically generated by MyBatis Generator, do not modify.
      This element was generated on Tue Sep 27 11:53:21 CST 2016.
    -->
    select
    <if test="distinct">
      distinct
    </if>
    'true' as QUERYID,
    <include refid="Base_Column_List" />
    from permission
    <if test="_parameter != null">
      <include refid="Example_Where_Clause" />
    </if>
    <if test="orderByClause != null">
      order by ${orderByClause}
    </if>
    <if test="pageOffSet !=0 or pageSize!=0">
      limit #{pageOffSet},#{pageSize}
    </if>
  </select>
  <select id="selectByPrimaryKey" parameterType="java.lang.Integer" resultMap="BaseResultMap">
    <!--
      WARNING - @mbggenerated
      This element is automatically generated by MyBatis Generator, do not modify.
      This element was generated on Tue Sep 27 11:53:21 CST 2016.
    -->
    select 
    <include refid="Base_Column_List" />
    from permission
    where id = #{id,jdbcType=INTEGER}
  </select>
  <delete id="deleteByPrimaryKey" parameterType="java.lang.Integer">
    <!--
      WARNING - @mbggenerated
      This element is automatically generated by MyBatis Generator, do not modify.
      This element was generated on Tue Sep 27 11:53:21 CST 2016.
    -->
    delete from permission
    where id = #{id,jdbcType=INTEGER}
  </delete>
  <delete id="deleteByExample" parameterType="com.dianrong.common.uniauth.server.data.entity.PermissionExample">
    <!--
      WARNING - @mbggenerated
      This element is automatically generated by MyBatis Generator, do not modify.
      This element was generated on Tue Sep 27 11:53:21 CST 2016.
    -->
    delete from permission
    <if test="_parameter != null">
      <include refid="Example_Where_Clause" />
    </if>
  </delete>
  <insert id="insert" parameterType="com.dianrong.common.uniauth.server.data.entity.Permission" useGeneratedKeys="true" keyProperty="id">
    <!--
      WARNING - @mbggenerated
      This element is automatically generated by MyBatis Generator, do not modify.
      This element was generated on Tue Sep 27 11:53:21 CST 2016.
    -->
    insert into permission (id, value, value_ext, 
      description, status, perm_type_id, 
      domain_id, tenancy_id)
    values (#{id,jdbcType=INTEGER}, #{value,jdbcType=VARCHAR}, #{valueExt,jdbcType=VARCHAR}, 
      #{description,jdbcType=VARCHAR}, #{status,jdbcType=TINYINT}, #{permTypeId,jdbcType=INTEGER}, 
      #{domainId,jdbcType=INTEGER}, #{tenancyId,jdbcType=BIGINT})
  </insert>
  <insert id="insertSelective" parameterType="com.dianrong.common.uniauth.server.data.entity.Permission" useGeneratedKeys="true" keyProperty="id">
    <!--
      WARNING - @mbggenerated
      This element is automatically generated by MyBatis Generator, do not modify.
      This element was generated on Tue Sep 27 11:53:21 CST 2016.
    -->
    insert into permission
    <trim prefix="(" suffix=")" suffixOverrides=",">
      <if test="id != null">
        id,
      </if>
      <if test="value != null">
        value,
      </if>
      <if test="valueExt != null">
        value_ext,
      </if>
      <if test="description != null">
        description,
      </if>
      <if test="status != null">
        status,
      </if>
      <if test="permTypeId != null">
        perm_type_id,
      </if>
      <if test="domainId != null">
        domain_id,
      </if>
      <if test="tenancyId != null">
        tenancy_id,
      </if>
    </trim>
    <trim prefix="values (" suffix=")" suffixOverrides=",">
      <if test="id != null">
        #{id,jdbcType=INTEGER},
      </if>
      <if test="value != null">
        #{value,jdbcType=VARCHAR},
      </if>
      <if test="valueExt != null">
        #{valueExt,jdbcType=VARCHAR},
      </if>
      <if test="description != null">
        #{description,jdbcType=VARCHAR},
      </if>
      <if test="status != null">
        #{status,jdbcType=TINYINT},
      </if>
      <if test="permTypeId != null">
        #{permTypeId,jdbcType=INTEGER},
      </if>
      <if test="domainId != null">
        #{domainId,jdbcType=INTEGER},
      </if>
      <if test="tenancyId != null">
        #{tenancyId,jdbcType=BIGINT},
      </if>
    </trim>
  </insert>
  <select id="countByExample" parameterType="com.dianrong.common.uniauth.server.data.entity.PermissionExample" resultType="java.lang.Integer">
    <!--
      WARNING - @mbggenerated
      This element is automatically generated by MyBatis Generator, do not modify.
      This element was generated on Tue Sep 27 11:53:21 CST 2016.
    -->
    select count(*) from permission
    <if test="_parameter != null">
      <include refid="Example_Where_Clause" />
    </if>
  </select>
  <update id="updateByExampleSelective" parameterType="map">
    <!--
      WARNING - @mbggenerated
      This element is automatically generated by MyBatis Generator, do not modify.
      This element was generated on Tue Sep 27 11:53:21 CST 2016.
    -->
    update permission
    <set>
      <if test="record.id != null">
        id = #{record.id,jdbcType=INTEGER},
      </if>
      <if test="record.value != null">
        value = #{record.value,jdbcType=VARCHAR},
      </if>
      <if test="record.valueExt != null">
        value_ext = #{record.valueExt,jdbcType=VARCHAR},
      </if>
      <if test="record.description != null">
        description = #{record.description,jdbcType=VARCHAR},
      </if>
      <if test="record.status != null">
        status = #{record.status,jdbcType=TINYINT},
      </if>
      <if test="record.permTypeId != null">
        perm_type_id = #{record.permTypeId,jdbcType=INTEGER},
      </if>
      <if test="record.domainId != null">
        domain_id = #{record.domainId,jdbcType=INTEGER},
      </if>
      <if test="record.tenancyId != null">
        tenancy_id = #{record.tenancyId,jdbcType=BIGINT},
      </if>
    </set>
    <if test="_parameter != null">
      <include refid="Update_By_Example_Where_Clause" />
    </if>
  </update>
  <update id="updateByExample" parameterType="map">
    <!--
      WARNING - @mbggenerated
      This element is automatically generated by MyBatis Generator, do not modify.
      This element was generated on Tue Sep 27 11:53:21 CST 2016.
    -->
    update permission
    set id = #{record.id,jdbcType=INTEGER},
      value = #{record.value,jdbcType=VARCHAR},
      value_ext = #{record.valueExt,jdbcType=VARCHAR},
      description = #{record.description,jdbcType=VARCHAR},
      status = #{record.status,jdbcType=TINYINT},
      perm_type_id = #{record.permTypeId,jdbcType=INTEGER},
      domain_id = #{record.domainId,jdbcType=INTEGER},
      tenancy_id = #{record.tenancyId,jdbcType=BIGINT}
    <if test="_parameter != null">
      <include refid="Update_By_Example_Where_Clause" />
    </if>
  </update>
  <update id="updateByPrimaryKeySelective" parameterType="com.dianrong.common.uniauth.server.data.entity.Permission">
    <!--
      WARNING - @mbggenerated
      This element is automatically generated by MyBatis Generator, do not modify.
      This element was generated on Tue Sep 27 11:53:21 CST 2016.
    -->
    update permission
    <set>
      <if test="value != null">
        value = #{value,jdbcType=VARCHAR},
      </if>
      <if test="valueExt != null">
        value_ext = #{valueExt,jdbcType=VARCHAR},
      </if>
      <if test="description != null">
        description = #{description,jdbcType=VARCHAR},
      </if>
      <if test="status != null">
        status = #{status,jdbcType=TINYINT},
      </if>
      <if test="permTypeId != null">
        perm_type_id = #{permTypeId,jdbcType=INTEGER},
      </if>
      <if test="domainId != null">
        domain_id = #{domainId,jdbcType=INTEGER},
      </if>
      <if test="tenancyId != null">
        tenancy_id = #{tenancyId,jdbcType=BIGINT},
      </if>
    </set>
    where id = #{id,jdbcType=INTEGER}
  </update>
  <update id="updateByPrimaryKey" parameterType="com.dianrong.common.uniauth.server.data.entity.Permission">
    <!--
      WARNING - @mbggenerated
      This element is automatically generated by MyBatis Generator, do not modify.
      This element was generated on Tue Sep 27 11:53:21 CST 2016.
    -->
    update permission
    set value = #{value,jdbcType=VARCHAR},
      value_ext = #{valueExt,jdbcType=VARCHAR},
      description = #{description,jdbcType=VARCHAR},
      status = #{status,jdbcType=TINYINT},
      perm_type_id = #{permTypeId,jdbcType=INTEGER},
      domain_id = #{domainId,jdbcType=INTEGER},
      tenancy_id = #{tenancyId,jdbcType=BIGINT}
    where id = #{id,jdbcType=INTEGER}
  </update>
</mapper>